graphsim/__init__.py
graphsim/graphsim.cpython-314-darwin.so
quantum_graphsim-0.1.1.dist-info/METADATA
quantum_graphsim-0.1.1.dist-info/WHEEL
quantum_graphsim-0.1.1.dist-info/RECORD
