Metadata-Version: 2.4
Name: quantum-graphsim
Version: 0.1.1
Classifier: Programming Language :: Rust
Classifier: Programming Language :: Python :: Implementation :: CPython
Classifier: Programming Language :: Python :: Implementation :: PyPy
Summary: A simple graph based simulator of qubits in the clifford set
Requires-Python: >=3.8
Project-URL: Homepage, https://github.com/itepastra/GraphSim
Project-URL: Issues, https://github.com/itepastra/GraphSim/issues
